odoo/addons/realestate/README.rst
odoo/addons/realestate/__init__.py
odoo/addons/realestate/__manifest__.py
odoo/addons/realestate/i18n/fr_BE.po
odoo/addons/realestate/i18n/realestate.pot
odoo/addons/realestate/models/__init__.py
odoo/addons/realestate/models/realestate_abstract_entity.py
odoo/addons/realestate/models/res_partner.py
odoo/addons/realestate/readme/CONTRIBUTORS.rst
odoo/addons/realestate/readme/DESCRIPTION.rst
odoo/addons/realestate/security/security.xml
odoo/addons/realestate/setup/.setuptools-odoo-make-default-ignore
odoo/addons/realestate/setup/README
odoo/addons/realestate/static/description/icon.png
odoo/addons/realestate/static/description/index.html
odoo/addons/realestate/tests/__init__.py
odoo/addons/realestate/tests/test_model.py
odoo/addons/realestate/tests/test_realestate.py
odoo/addons/realestate/views/menus.xml
odoo/addons/realestate/views/realestate_abstract_entity.xml
odoo13_addon_realestate-13.0.1.0.2.dist-info/METADATA
odoo13_addon_realestate-13.0.1.0.2.dist-info/WHEEL
odoo13_addon_realestate-13.0.1.0.2.dist-info/top_level.txt
odoo13_addon_realestate-13.0.1.0.2.dist-info/RECORD
